{"data":[{"id":"8b69c1f5-f53c-455d-98fa-6fc6226d7417","productId":"0192b414-947e-42be-a5fc-f13f7f70739d","url":"https://www.heomedia.com/img/nrm/x_mngm29195.jpg","caption":null,"order":0,"createdAt":"2025-04-16T22:59:20.164Z","updatedAt":"2025-04-16T22:59:20.164Z","deletedAt":null},{"id":"a2d5bc31-9c2b-4ff3-b0fb-6f2c652df1f4","productId":"0192b414-947e-42be-a5fc-f13f7f70739d","url":"https://www.heomedia.com/img/nrm/x_mngm29195_a.jpg","caption":null,"order":1,"createdAt":"2025-04-16T22:59:20.247Z","updatedAt":"2025-04-16T22:59:20.247Z","deletedAt":null},{"id":"d34b6f47-16b5-4318-a212-e3a37910aaa0","productId":"0192b414-947e-42be-a5fc-f13f7f70739d","url":"https://www.heomedia.com/img/nrm/x_mngm29195_b.jpg","caption":null,"order":2,"createdAt":"2025-04-16T22:59:20.275Z","updatedAt":"2025-04-16T22:59:20.275Z","deletedAt":null}]}