{"data":[{"id":"a0da76c0-a86a-419b-850d-9674bbc97b09","productId":"210ef68c-254b-4d7b-86df-483b3fcf6398","url":"https://www.heomedia.com/img/nrm/x_weta115004340.jpg","caption":null,"order":0,"createdAt":"2025-03-28T02:41:34.613Z","updatedAt":"2025-03-28T02:41:34.613Z","deletedAt":null},{"id":"a8ce743e-f096-4ea2-98da-bfa6f54ebe6e","productId":"210ef68c-254b-4d7b-86df-483b3fcf6398","url":"https://www.heomedia.com/img/nrm/x_weta115004340_a.jpg","caption":null,"order":1,"createdAt":"2025-03-28T02:41:34.674Z","updatedAt":"2025-03-28T02:41:34.674Z","deletedAt":null},{"id":"06aacbe2-98d8-4431-a207-8378c32a9532","productId":"210ef68c-254b-4d7b-86df-483b3fcf6398","url":"https://www.heomedia.com/img/nrm/x_weta115004340_b.jpg","caption":null,"order":2,"createdAt":"2025-03-28T02:41:34.692Z","updatedAt":"2025-03-28T02:41:34.692Z","deletedAt":null},{"id":"0ee05902-82d7-4080-809e-129028bbf072","productId":"210ef68c-254b-4d7b-86df-483b3fcf6398","url":"https://www.heomedia.com/img/nrm/x_weta115004340_c.jpg","caption":null,"order":3,"createdAt":"2025-03-28T02:41:34.711Z","updatedAt":"2025-03-28T02:41:34.711Z","deletedAt":null},{"id":"8fb791a7-2c50-4853-884c-80a61521534d","productId":"210ef68c-254b-4d7b-86df-483b3fcf6398","url":"https://www.heomedia.com/img/nrm/x_weta115004340_d.jpg","caption":null,"order":4,"createdAt":"2025-03-28T02:41:34.729Z","updatedAt":"2025-03-28T02:41:34.729Z","deletedAt":null},{"id":"07cd9eec-c544-4505-a39b-e2d7eb1728b7","productId":"210ef68c-254b-4d7b-86df-483b3fcf6398","url":"https://www.heomedia.com/img/nrm/x_weta115004340_e.jpg","caption":null,"order":5,"createdAt":"2025-03-28T02:41:34.753Z","updatedAt":"2025-03-28T02:41:34.753Z","deletedAt":null},{"id":"4174908a-7cab-4ec4-b628-b72125c0d3e3","productId":"210ef68c-254b-4d7b-86df-483b3fcf6398","url":"https://www.heomedia.com/img/nrm/x_weta115004340_f.jpg","caption":null,"order":6,"createdAt":"2025-03-28T02:41:34.772Z","updatedAt":"2025-03-28T02:41:34.772Z","deletedAt":null},{"id":"2032bb0d-c13a-4698-affd-c364b4c4ea90","productId":"210ef68c-254b-4d7b-86df-483b3fcf6398","url":"https://www.heomedia.com/img/nrm/x_weta115004340_g.jpg","caption":null,"order":7,"createdAt":"2025-03-28T02:41:34.790Z","updatedAt":"2025-03-28T02:41:34.790Z","deletedAt":null},{"id":"d2e3d23d-3ca5-4579-9e4f-25daa6377c34","productId":"210ef68c-254b-4d7b-86df-483b3fcf6398","url":"https://www.heomedia.com/img/nrm/x_weta115004340_h.jpg","caption":null,"order":8,"createdAt":"2025-03-28T02:41:34.809Z","updatedAt":"2025-03-28T02:41:34.809Z","deletedAt":null}]}