{"data":[{"id":"f1ba9fd4-55a3-4426-a002-3301956553c2","productId":"30da77fb-f3a8-4162-862b-23dd4861cc93","url":"https://www.heomedia.com/img/nrm/x_fk74276.jpg","caption":null,"order":0,"createdAt":"2025-03-28T00:09:40.009Z","updatedAt":"2025-03-28T00:09:40.009Z","deletedAt":null},{"id":"8fd1abbc-be3b-4e3f-8de0-dbb8a8ae74c8","productId":"30da77fb-f3a8-4162-862b-23dd4861cc93","url":"https://www.heomedia.com/img/nrm/x_fk74276_a.jpg","caption":null,"order":1,"createdAt":"2025-03-28T00:09:40.206Z","updatedAt":"2025-03-28T00:09:40.206Z","deletedAt":null}]}