{"data":[{"id":"cd91f656-94b9-427b-bd4e-a1744814bcbc","productId":"321260c3-d5d5-4104-9bee-90a30b1d028f","url":"https://www.heomedia.com/img/nrm/x_fk83495.jpg","caption":null,"order":0,"createdAt":"2025-03-28T00:17:51.019Z","updatedAt":"2025-03-28T00:17:51.019Z","deletedAt":null},{"id":"648af4b8-cdce-4934-b279-14d530e8ae61","productId":"321260c3-d5d5-4104-9bee-90a30b1d028f","url":"https://www.heomedia.com/img/nrm/x_fk83495_a.jpg","caption":null,"order":1,"createdAt":"2025-03-28T00:17:51.113Z","updatedAt":"2025-03-28T00:17:51.113Z","deletedAt":null}]}