{"data":[{"id":"b5ac9fba-092e-420d-aed1-8661ec4a1070","productId":"4cb7564f-4ac1-44d9-b757-3659ef2c595b","url":"https://www.heomedia.com/img/nrm/x_hbsa16095.jpg","caption":null,"order":0,"createdAt":"2025-04-11T17:40:26.055Z","updatedAt":"2025-04-11T17:40:26.055Z","deletedAt":null},{"id":"57cb6194-4265-4d89-878b-4cac5751e9ae","productId":"4cb7564f-4ac1-44d9-b757-3659ef2c595b","url":"https://www.heomedia.com/img/nrm/x_hbsa16095_a.jpg","caption":null,"order":1,"createdAt":"2025-04-11T17:40:26.160Z","updatedAt":"2025-04-11T17:40:26.160Z","deletedAt":null},{"id":"bb9ccb6a-c27e-4597-ab92-6cb42a4d5dbf","productId":"4cb7564f-4ac1-44d9-b757-3659ef2c595b","url":"https://www.heomedia.com/img/nrm/x_hbsa16095_b.jpg","caption":null,"order":2,"createdAt":"2025-04-11T17:40:26.193Z","updatedAt":"2025-04-11T17:40:26.193Z","deletedAt":null},{"id":"10152632-4e89-4b3d-80c4-f114b8f22cf3","productId":"4cb7564f-4ac1-44d9-b757-3659ef2c595b","url":"https://www.heomedia.com/img/nrm/x_hbsa16095_c.jpg","caption":null,"order":3,"createdAt":"2025-04-11T17:40:26.232Z","updatedAt":"2025-04-11T17:40:26.232Z","deletedAt":null},{"id":"7cfb20d8-84f9-4e8a-987b-4dc1eb118bfc","productId":"4cb7564f-4ac1-44d9-b757-3659ef2c595b","url":"https://www.heomedia.com/img/nrm/x_hbsa16095_d.jpg","caption":null,"order":4,"createdAt":"2025-04-11T17:40:26.266Z","updatedAt":"2025-04-11T17:40:26.266Z","deletedAt":null},{"id":"51d237af-d764-4397-b558-d598042580ab","productId":"4cb7564f-4ac1-44d9-b757-3659ef2c595b","url":"https://www.heomedia.com/img/nrm/x_hbsa16095_e.jpg","caption":null,"order":5,"createdAt":"2025-04-11T17:40:26.300Z","updatedAt":"2025-04-11T17:40:26.300Z","deletedAt":null},{"id":"6a045259-264f-49b3-b2eb-9977208dbbd3","productId":"4cb7564f-4ac1-44d9-b757-3659ef2c595b","url":"https://www.heomedia.com/img/nrm/x_hbsa16095_f.jpg","caption":null,"order":6,"createdAt":"2025-04-11T17:40:26.335Z","updatedAt":"2025-04-11T17:40:26.335Z","deletedAt":null},{"id":"8ef2cadc-64ef-419f-8c4e-b92876e3f7e9","productId":"4cb7564f-4ac1-44d9-b757-3659ef2c595b","url":"https://www.heomedia.com/img/nrm/x_hbsa16095_g.jpg","caption":null,"order":7,"createdAt":"2025-04-11T17:40:26.387Z","updatedAt":"2025-04-11T17:40:26.387Z","deletedAt":null},{"id":"6a8a4d44-413b-407b-9f08-fd8e8986ea27","productId":"4cb7564f-4ac1-44d9-b757-3659ef2c595b","url":"https://www.heomedia.com/img/nrm/x_hbsa16095_h.jpg","caption":null,"order":8,"createdAt":"2025-04-11T17:40:26.415Z","updatedAt":"2025-04-11T17:40:26.415Z","deletedAt":null},{"id":"1db51d20-a947-4a42-9eae-50c9fa876db4","productId":"4cb7564f-4ac1-44d9-b757-3659ef2c595b","url":"https://www.heomedia.com/img/nrm/x_hbsa16095_i.jpg","caption":null,"order":9,"createdAt":"2025-04-11T17:40:26.454Z","updatedAt":"2025-04-11T17:40:26.454Z","deletedAt":null},{"id":"bc106d56-17d9-430e-9bea-56fa2fc67998","productId":"4cb7564f-4ac1-44d9-b757-3659ef2c595b","url":"https://www.heomedia.com/img/nrm/x_hbsa16095_j.jpg","caption":null,"order":10,"createdAt":"2025-04-11T17:40:26.516Z","updatedAt":"2025-04-11T17:40:26.516Z","deletedAt":null},{"id":"07b4616d-c00b-482c-b560-e22cb59ad347","productId":"4cb7564f-4ac1-44d9-b757-3659ef2c595b","url":"https://www.heomedia.com/img/nrm/x_hbsa16095_k.jpg","caption":null,"order":11,"createdAt":"2025-04-11T17:40:26.547Z","updatedAt":"2025-04-11T17:40:26.547Z","deletedAt":null},{"id":"26fe3e98-91c9-43f9-a147-13dfb4b87682","productId":"4cb7564f-4ac1-44d9-b757-3659ef2c595b","url":"https://www.heomedia.com/img/nrm/x_hbsa16095_l.jpg","caption":null,"order":12,"createdAt":"2025-04-11T17:40:26.585Z","updatedAt":"2025-04-11T17:40:26.585Z","deletedAt":null},{"id":"ade43834-1ccd-4427-95ed-e339f20b99b9","productId":"4cb7564f-4ac1-44d9-b757-3659ef2c595b","url":"https://www.heomedia.com/img/nrm/x_hbsa16095_m.jpg","caption":null,"order":13,"createdAt":"2025-04-11T17:40:26.640Z","updatedAt":"2025-04-11T17:40:26.640Z","deletedAt":null},{"id":"e141bf4f-76a3-4a60-80f9-fa1e89997036","productId":"4cb7564f-4ac1-44d9-b757-3659ef2c595b","url":"https://www.heomedia.com/img/nrm/x_hbsa16095_n.jpg","caption":null,"order":14,"createdAt":"2025-04-11T17:40:26.674Z","updatedAt":"2025-04-11T17:40:26.674Z","deletedAt":null},{"id":"2c2c28dd-38a5-43ce-a7d6-74a627bfb4de","productId":"4cb7564f-4ac1-44d9-b757-3659ef2c595b","url":"https://www.heomedia.com/img/nrm/x_hbsa16095_o.jpg","caption":null,"order":15,"createdAt":"2025-04-11T17:40:26.711Z","updatedAt":"2025-04-11T17:40:26.711Z","deletedAt":null},{"id":"9d9bc49f-3aba-4e33-b729-81993cbc3fe3","productId":"4cb7564f-4ac1-44d9-b757-3659ef2c595b","url":"https://www.heomedia.com/img/nrm/x_hbsa16095_p.jpg","caption":null,"order":16,"createdAt":"2025-04-11T17:40:26.750Z","updatedAt":"2025-04-11T17:40:26.750Z","deletedAt":null},{"id":"f0f45a15-2738-4f26-9f4d-ae3fae13cf1e","productId":"4cb7564f-4ac1-44d9-b757-3659ef2c595b","url":"https://www.heomedia.com/img/nrm/x_hbsa16095_q.jpg","caption":null,"order":17,"createdAt":"2025-04-11T17:40:26.785Z","updatedAt":"2025-04-11T17:40:26.785Z","deletedAt":null},{"id":"ae633d56-f985-4df7-bba2-40c8f60b4df1","productId":"4cb7564f-4ac1-44d9-b757-3659ef2c595b","url":"https://www.heomedia.com/img/nrm/x_hbsa16095_r.jpg","caption":null,"order":18,"createdAt":"2025-04-11T17:40:26.822Z","updatedAt":"2025-04-11T17:40:26.822Z","deletedAt":null},{"id":"17ea5803-edb9-4896-b840-a584f16c1c5d","productId":"4cb7564f-4ac1-44d9-b757-3659ef2c595b","url":"https://www.heomedia.com/img/nrm/x_hbsa16095_s.jpg","caption":null,"order":19,"createdAt":"2025-04-11T17:40:26.856Z","updatedAt":"2025-04-11T17:40:26.856Z","deletedAt":null}]}