{"data":[{"id":"382a3059-d55c-41a5-bb6f-f40d09221892","productId":"4e34c607-a695-402a-9557-63a996d216be","url":"https://www.heomedia.com/img/nrm/x_bkdds-122.jpg","caption":null,"order":0,"createdAt":"2025-03-27T23:41:54.614Z","updatedAt":"2025-03-27T23:41:54.614Z","deletedAt":null},{"id":"1fafbbb4-9fb2-47a3-a453-733e7bab5848","productId":"4e34c607-a695-402a-9557-63a996d216be","url":"https://www.heomedia.com/img/nrm/x_bkdds-122_a.jpg","caption":null,"order":1,"createdAt":"2025-03-27T23:41:54.769Z","updatedAt":"2025-03-27T23:41:54.769Z","deletedAt":null},{"id":"874a49da-dc85-4905-97f7-b51d29dc1bc7","productId":"4e34c607-a695-402a-9557-63a996d216be","url":"https://www.heomedia.com/img/nrm/x_bkdds-122_b.jpg","caption":null,"order":2,"createdAt":"2025-03-27T23:41:54.789Z","updatedAt":"2025-03-27T23:41:54.789Z","deletedAt":null},{"id":"b6757c23-74ca-4d19-8407-94b8127f9d47","productId":"4e34c607-a695-402a-9557-63a996d216be","url":"https://www.heomedia.com/img/nrm/x_bkdds-122_c.jpg","caption":null,"order":3,"createdAt":"2025-03-27T23:41:54.810Z","updatedAt":"2025-03-27T23:41:54.810Z","deletedAt":null},{"id":"8bc4a4a4-fe8f-4dee-ab28-d669785aaf00","productId":"4e34c607-a695-402a-9557-63a996d216be","url":"https://www.heomedia.com/img/nrm/x_bkdds-122_d.jpg","caption":null,"order":4,"createdAt":"2025-03-27T23:41:54.830Z","updatedAt":"2025-03-27T23:41:54.830Z","deletedAt":null},{"id":"42719481-48fc-4056-a68e-a27a936844d3","productId":"4e34c607-a695-402a-9557-63a996d216be","url":"https://www.heomedia.com/img/nrm/x_bkdds-122_e.jpg","caption":null,"order":5,"createdAt":"2025-03-27T23:41:54.851Z","updatedAt":"2025-03-27T23:41:54.851Z","deletedAt":null},{"id":"7c7f9a3d-ddc3-4324-98a2-bbb7cd9b74f4","productId":"4e34c607-a695-402a-9557-63a996d216be","url":"https://www.heomedia.com/img/nrm/x_bkdds-122_f.jpg","caption":null,"order":6,"createdAt":"2025-03-27T23:41:54.872Z","updatedAt":"2025-03-27T23:41:54.872Z","deletedAt":null},{"id":"9ffb2b1a-1fbe-4e20-89a2-4b68e2c6409a","productId":"4e34c607-a695-402a-9557-63a996d216be","url":"https://www.heomedia.com/img/nrm/x_bkdds-122_g.jpg","caption":null,"order":7,"createdAt":"2025-03-27T23:41:54.893Z","updatedAt":"2025-03-27T23:41:54.893Z","deletedAt":null}]}