{"data":[{"id":"dd62af2f-7b39-43c8-a80e-71bcb70ded44","productId":"6534f5f1-fb7f-4fb9-b210-701c651f56ef","url":"https://www.heomedia.com/img/nrm/x_crtwe0054.jpg","caption":null,"order":0,"createdAt":"2025-03-27T23:54:29.861Z","updatedAt":"2025-03-27T23:54:29.861Z","deletedAt":null},{"id":"da68e75d-0392-4dd7-a30a-7723eeed0b18","productId":"6534f5f1-fb7f-4fb9-b210-701c651f56ef","url":"https://www.heomedia.com/img/nrm/x_crtwe0054_a.jpg","caption":null,"order":1,"createdAt":"2025-03-27T23:54:29.969Z","updatedAt":"2025-03-27T23:54:29.969Z","deletedAt":null}]}