{"data":[{"id":"b12c7e86-46cc-46da-82f4-175d975a64be","productId":"6de98fa1-1037-4ec9-9f96-70d735ad0626","url":"https://www.heomedia.com/img/nrm/x_gohe91807.jpg","caption":null,"order":0,"createdAt":"2025-03-28T00:29:53.871Z","updatedAt":"2025-03-28T00:29:53.871Z","deletedAt":null},{"id":"66e99bf5-6b9d-4466-a6d7-d809d99f9a63","productId":"6de98fa1-1037-4ec9-9f96-70d735ad0626","url":"https://www.heomedia.com/img/nrm/x_gohe91807_a.jpg","caption":null,"order":1,"createdAt":"2025-03-28T00:29:54.000Z","updatedAt":"2025-03-28T00:29:54.000Z","deletedAt":null},{"id":"590cd2e8-3725-47c3-8238-7c451a2b1a26","productId":"6de98fa1-1037-4ec9-9f96-70d735ad0626","url":"https://www.heomedia.com/img/nrm/x_gohe91807_b.jpg","caption":null,"order":2,"createdAt":"2025-03-28T00:29:54.020Z","updatedAt":"2025-03-28T00:29:54.020Z","deletedAt":null},{"id":"458c099e-765e-4be9-9ce0-1faea3d08fda","productId":"6de98fa1-1037-4ec9-9f96-70d735ad0626","url":"https://www.heomedia.com/img/nrm/x_gohe91807_c.jpg","caption":null,"order":3,"createdAt":"2025-03-28T00:29:54.039Z","updatedAt":"2025-03-28T00:29:54.039Z","deletedAt":null},{"id":"678504d8-beaa-42bb-844a-aa33cc4d4bd6","productId":"6de98fa1-1037-4ec9-9f96-70d735ad0626","url":"https://www.heomedia.com/img/nrm/x_gohe91807_d.jpg","caption":null,"order":4,"createdAt":"2025-03-28T00:29:54.059Z","updatedAt":"2025-03-28T00:29:54.059Z","deletedAt":null},{"id":"5d825eda-0d61-4346-a075-4d2985edebb4","productId":"6de98fa1-1037-4ec9-9f96-70d735ad0626","url":"https://www.heomedia.com/img/nrm/x_gohe91807_e.jpg","caption":null,"order":5,"createdAt":"2025-03-28T00:29:54.078Z","updatedAt":"2025-03-28T00:29:54.078Z","deletedAt":null},{"id":"bf50e280-888f-40fb-9aa1-64f875570764","productId":"6de98fa1-1037-4ec9-9f96-70d735ad0626","url":"https://www.heomedia.com/img/nrm/x_gohe91807_f.jpg","caption":null,"order":6,"createdAt":"2025-03-28T00:29:54.098Z","updatedAt":"2025-03-28T00:29:54.098Z","deletedAt":null},{"id":"9e659cf5-277e-4546-bffe-e5dbaac1b31c","productId":"6de98fa1-1037-4ec9-9f96-70d735ad0626","url":"https://www.heomedia.com/img/nrm/x_gohe91807_g.jpg","caption":null,"order":7,"createdAt":"2025-03-28T00:29:54.118Z","updatedAt":"2025-03-28T00:29:54.118Z","deletedAt":null},{"id":"448ba26b-bf48-4585-bc4b-1f77a65a8f1e","productId":"6de98fa1-1037-4ec9-9f96-70d735ad0626","url":"https://www.heomedia.com/img/nrm/x_gohe91807_h.jpg","caption":null,"order":8,"createdAt":"2025-03-28T00:29:54.138Z","updatedAt":"2025-03-28T00:29:54.138Z","deletedAt":null},{"id":"43d23e72-891d-4f41-a8f0-194dc10847b3","productId":"6de98fa1-1037-4ec9-9f96-70d735ad0626","url":"https://www.heomedia.com/img/nrm/x_gohe91807_i.jpg","caption":null,"order":9,"createdAt":"2025-03-28T00:29:54.160Z","updatedAt":"2025-03-28T00:29:54.160Z","deletedAt":null},{"id":"ed0ae7a7-70d9-49e3-84e8-c60d094b5405","productId":"6de98fa1-1037-4ec9-9f96-70d735ad0626","url":"https://www.heomedia.com/img/nrm/x_gohe91807_j.jpg","caption":null,"order":10,"createdAt":"2025-03-28T00:29:54.183Z","updatedAt":"2025-03-28T00:29:54.183Z","deletedAt":null},{"id":"d052f4ce-ef81-42de-8f6b-60420e3ca63a","productId":"6de98fa1-1037-4ec9-9f96-70d735ad0626","url":"https://www.heomedia.com/img/nrm/x_gohe91807_k.jpg","caption":null,"order":11,"createdAt":"2025-03-28T00:29:54.202Z","updatedAt":"2025-03-28T00:29:54.202Z","deletedAt":null},{"id":"763d7ee0-bb0d-4198-81d8-078c8f877206","productId":"6de98fa1-1037-4ec9-9f96-70d735ad0626","url":"https://www.heomedia.com/img/nrm/x_gohe91807_l.jpg","caption":null,"order":12,"createdAt":"2025-03-28T00:29:54.222Z","updatedAt":"2025-03-28T00:29:54.222Z","deletedAt":null},{"id":"b5004bab-e600-48a8-b950-2f147e9ed36a","productId":"6de98fa1-1037-4ec9-9f96-70d735ad0626","url":"https://www.heomedia.com/img/nrm/x_gohe91807_m.jpg","caption":null,"order":13,"createdAt":"2025-03-28T00:29:54.241Z","updatedAt":"2025-03-28T00:29:54.241Z","deletedAt":null},{"id":"ed571b2b-31a4-4858-85a8-ca87f4d6e46d","productId":"6de98fa1-1037-4ec9-9f96-70d735ad0626","url":"https://www.heomedia.com/img/nrm/x_gohe91807_n.jpg","caption":null,"order":14,"createdAt":"2025-03-28T00:29:54.260Z","updatedAt":"2025-03-28T00:29:54.260Z","deletedAt":null},{"id":"cd492fff-bf6b-4ae9-a914-776522617122","productId":"6de98fa1-1037-4ec9-9f96-70d735ad0626","url":"https://www.heomedia.com/img/nrm/x_gohe91807_o.jpg","caption":null,"order":15,"createdAt":"2025-03-28T00:29:54.280Z","updatedAt":"2025-03-28T00:29:54.280Z","deletedAt":null},{"id":"4ad75575-e0cf-42f3-9233-0629f7e3ff3b","productId":"6de98fa1-1037-4ec9-9f96-70d735ad0626","url":"https://www.heomedia.com/img/nrm/x_gohe91807_p.jpg","caption":null,"order":16,"createdAt":"2025-03-28T00:29:54.300Z","updatedAt":"2025-03-28T00:29:54.300Z","deletedAt":null},{"id":"60d3c343-2fc0-41b7-9cea-66da5501d34e","productId":"6de98fa1-1037-4ec9-9f96-70d735ad0626","url":"https://www.heomedia.com/img/nrm/x_gohe91807_q.jpg","caption":null,"order":17,"createdAt":"2025-03-28T00:29:54.319Z","updatedAt":"2025-03-28T00:29:54.319Z","deletedAt":null},{"id":"f01d5b73-9043-4224-bda6-660f3f85f7cd","productId":"6de98fa1-1037-4ec9-9f96-70d735ad0626","url":"https://www.heomedia.com/img/nrm/x_gohe91807_r.jpg","caption":null,"order":18,"createdAt":"2025-03-28T00:29:54.340Z","updatedAt":"2025-03-28T00:29:54.340Z","deletedAt":null},{"id":"fefe4e86-dc59-459f-965a-56e5a1ed231d","productId":"6de98fa1-1037-4ec9-9f96-70d735ad0626","url":"https://www.heomedia.com/img/nrm/x_gohe91807_s.jpg","caption":null,"order":19,"createdAt":"2025-03-28T00:29:54.360Z","updatedAt":"2025-03-28T00:29:54.360Z","deletedAt":null},{"id":"1d27db47-f7c3-4959-9090-4f88cbe281fe","productId":"6de98fa1-1037-4ec9-9f96-70d735ad0626","url":"https://www.heomedia.com/img/nrm/x_gohe91807_t.jpg","caption":null,"order":20,"createdAt":"2025-03-28T00:29:54.380Z","updatedAt":"2025-03-28T00:29:54.380Z","deletedAt":null}]}