{"data":[{"id":"8174f192-a6dc-40b2-8407-2a63a5907d4a","productId":"7d7fd232-2546-4c09-9ddd-2a017635747e","url":"https://www.heomedia.com/img/nrm/x_tekn811652.jpg","caption":null,"order":0,"createdAt":"2025-03-28T02:28:44.802Z","updatedAt":"2025-03-28T02:28:44.802Z","deletedAt":null},{"id":"8d6022ee-e433-4b4e-b785-5c6b3c1ee3e3","productId":"7d7fd232-2546-4c09-9ddd-2a017635747e","url":"https://www.heomedia.com/img/nrm/x_tekn811652_a.jpg","caption":null,"order":1,"createdAt":"2025-03-28T02:28:44.937Z","updatedAt":"2025-03-28T02:28:44.937Z","deletedAt":null}]}