{"data":[{"id":"1e651a0f-795d-4c86-b927-bdee7b8dd756","productId":"8630c12e-ea46-488f-b56a-f1589ebed02d","url":"https://www.heomedia.com/img/nrm/x_apex42202.jpg","caption":null,"order":0,"createdAt":"2025-03-27T23:33:53.842Z","updatedAt":"2025-03-27T23:33:53.842Z","deletedAt":null},{"id":"41bced55-df5a-484d-bd44-2ba7ebbb5787","productId":"8630c12e-ea46-488f-b56a-f1589ebed02d","url":"https://www.heomedia.com/img/nrm/x_apex42202_a.jpg","caption":null,"order":1,"createdAt":"2025-03-27T23:33:54.135Z","updatedAt":"2025-03-27T23:33:54.135Z","deletedAt":null},{"id":"2d52d13f-5350-4eeb-8c72-33db6573f61d","productId":"8630c12e-ea46-488f-b56a-f1589ebed02d","url":"https://www.heomedia.com/img/nrm/x_apex42202_b.jpg","caption":null,"order":2,"createdAt":"2025-03-27T23:33:54.145Z","updatedAt":"2025-03-27T23:33:54.145Z","deletedAt":null},{"id":"2f172aaf-3021-4455-82ec-e3c6a03d238e","productId":"8630c12e-ea46-488f-b56a-f1589ebed02d","url":"https://www.heomedia.com/img/nrm/x_apex42202_c.jpg","caption":null,"order":3,"createdAt":"2025-03-27T23:33:54.153Z","updatedAt":"2025-03-27T23:33:54.153Z","deletedAt":null},{"id":"d101fc8f-c679-4bf3-aec1-8b842a09be40","productId":"8630c12e-ea46-488f-b56a-f1589ebed02d","url":"https://www.heomedia.com/img/nrm/x_apex42202_d.jpg","caption":null,"order":4,"createdAt":"2025-03-27T23:33:54.161Z","updatedAt":"2025-03-27T23:33:54.161Z","deletedAt":null},{"id":"4f012c6c-5276-40c5-b5e0-edd665350810","productId":"8630c12e-ea46-488f-b56a-f1589ebed02d","url":"https://www.heomedia.com/img/nrm/x_apex42202_e.jpg","caption":null,"order":5,"createdAt":"2025-03-27T23:33:54.169Z","updatedAt":"2025-03-27T23:33:54.169Z","deletedAt":null},{"id":"79f62276-1e2a-415f-8c70-b10b29b51a35","productId":"8630c12e-ea46-488f-b56a-f1589ebed02d","url":"https://www.heomedia.com/img/nrm/x_apex42202_f.jpg","caption":null,"order":6,"createdAt":"2025-03-27T23:33:54.177Z","updatedAt":"2025-03-27T23:33:54.177Z","deletedAt":null},{"id":"ba608e2a-6b07-4431-9eab-098e6efea3d5","productId":"8630c12e-ea46-488f-b56a-f1589ebed02d","url":"https://www.heomedia.com/img/nrm/x_apex42202_g.jpg","caption":null,"order":7,"createdAt":"2025-03-27T23:33:54.185Z","updatedAt":"2025-03-27T23:33:54.185Z","deletedAt":null},{"id":"d10c5f40-75cc-4011-97ab-0ca548a5327b","productId":"8630c12e-ea46-488f-b56a-f1589ebed02d","url":"https://www.heomedia.com/img/nrm/x_apex42202_h.jpg","caption":null,"order":8,"createdAt":"2025-03-27T23:33:54.194Z","updatedAt":"2025-03-27T23:33:54.194Z","deletedAt":null},{"id":"1973d416-63ee-4760-b162-2f4cb23d41ca","productId":"8630c12e-ea46-488f-b56a-f1589ebed02d","url":"https://www.heomedia.com/img/nrm/x_apex42202_i.jpg","caption":null,"order":9,"createdAt":"2025-03-27T23:33:54.201Z","updatedAt":"2025-03-27T23:33:54.201Z","deletedAt":null},{"id":"cbe34fca-482c-4e41-abb7-76cb4d648f62","productId":"8630c12e-ea46-488f-b56a-f1589ebed02d","url":"https://www.heomedia.com/img/nrm/x_apex42202_j.jpg","caption":null,"order":10,"createdAt":"2025-03-27T23:33:54.209Z","updatedAt":"2025-03-27T23:33:54.209Z","deletedAt":null},{"id":"5d63a68f-6243-4435-9a44-f87530d29b68","productId":"8630c12e-ea46-488f-b56a-f1589ebed02d","url":"https://www.heomedia.com/img/nrm/x_apex42202_k.jpg","caption":null,"order":11,"createdAt":"2025-03-27T23:33:54.219Z","updatedAt":"2025-03-27T23:33:54.219Z","deletedAt":null},{"id":"695dc849-05df-455e-ba83-bf0e8c450e01","productId":"8630c12e-ea46-488f-b56a-f1589ebed02d","url":"https://www.heomedia.com/img/nrm/x_apex42202_l.jpg","caption":null,"order":12,"createdAt":"2025-03-27T23:33:54.229Z","updatedAt":"2025-03-27T23:33:54.229Z","deletedAt":null}]}