{"data":[{"id":"d61e9793-de0e-402d-952d-9f4f90ead839","productId":"88127923-db6e-4262-bf3c-933db957456a","url":"https://www.heomedia.com/img/nrm/x_pkaagi-5057.jpg","caption":null,"order":0,"createdAt":"2025-04-11T17:41:48.553Z","updatedAt":"2025-04-11T17:41:48.553Z","deletedAt":null},{"id":"19307c6a-fa59-4dd0-a46a-41da49257715","productId":"88127923-db6e-4262-bf3c-933db957456a","url":"https://www.heomedia.com/img/nrm/x_pkaagi-5057_a.jpg","caption":null,"order":1,"createdAt":"2025-04-11T17:41:48.619Z","updatedAt":"2025-04-11T17:41:48.619Z","deletedAt":null}]}