{"data":[{"id":"dee1d667-7f95-422e-b489-8d88a050f342","productId":"9d6e3e40-0cfd-462e-b4fd-9470cc406fbe","url":"https://www.heomedia.com/img/nrm/x_bind60269.jpg","caption":null,"order":0,"createdAt":"2025-03-27T23:41:10.778Z","updatedAt":"2025-03-27T23:41:10.778Z","deletedAt":null},{"id":"bcb84484-70e0-40c3-8083-2d23f9bf29c5","productId":"9d6e3e40-0cfd-462e-b4fd-9470cc406fbe","url":"https://www.heomedia.com/img/nrm/x_bind60269_a.jpg","caption":null,"order":1,"createdAt":"2025-03-27T23:41:10.942Z","updatedAt":"2025-03-27T23:41:10.942Z","deletedAt":null},{"id":"c762ff0c-2b85-408a-bce2-3875f526ea35","productId":"9d6e3e40-0cfd-462e-b4fd-9470cc406fbe","url":"https://www.heomedia.com/img/nrm/x_bind60269_b.jpg","caption":null,"order":2,"createdAt":"2025-03-27T23:41:10.963Z","updatedAt":"2025-03-27T23:41:10.963Z","deletedAt":null},{"id":"ab451dc9-536b-4a9d-8889-e3fdbb57d367","productId":"9d6e3e40-0cfd-462e-b4fd-9470cc406fbe","url":"https://www.heomedia.com/img/nrm/x_bind60269_c.jpg","caption":null,"order":3,"createdAt":"2025-03-27T23:41:10.983Z","updatedAt":"2025-03-27T23:41:10.983Z","deletedAt":null},{"id":"bb2a7eab-4c6c-419f-aa1e-3debe4447290","productId":"9d6e3e40-0cfd-462e-b4fd-9470cc406fbe","url":"https://www.heomedia.com/img/nrm/x_bind60269_d.jpg","caption":null,"order":4,"createdAt":"2025-03-27T23:41:11.004Z","updatedAt":"2025-03-27T23:41:11.004Z","deletedAt":null},{"id":"510cd19f-0f47-4e64-9f48-124694bd4671","productId":"9d6e3e40-0cfd-462e-b4fd-9470cc406fbe","url":"https://www.heomedia.com/img/nrm/x_bind60269_e.jpg","caption":null,"order":5,"createdAt":"2025-03-27T23:41:11.024Z","updatedAt":"2025-03-27T23:41:11.024Z","deletedAt":null},{"id":"46d53b1e-eb62-4005-b5e5-28fefc445bb3","productId":"9d6e3e40-0cfd-462e-b4fd-9470cc406fbe","url":"https://www.heomedia.com/img/nrm/x_bind60269_f.jpg","caption":null,"order":6,"createdAt":"2025-03-27T23:41:11.044Z","updatedAt":"2025-03-27T23:41:11.044Z","deletedAt":null},{"id":"070d80ad-aa26-45d6-b4d6-fb56bb21bf93","productId":"9d6e3e40-0cfd-462e-b4fd-9470cc406fbe","url":"https://www.heomedia.com/img/nrm/x_bind60269_g.jpg","caption":null,"order":7,"createdAt":"2025-03-27T23:41:11.064Z","updatedAt":"2025-03-27T23:41:11.064Z","deletedAt":null},{"id":"6e929969-9021-489a-8b8a-820e87883075","productId":"9d6e3e40-0cfd-462e-b4fd-9470cc406fbe","url":"https://www.heomedia.com/img/nrm/x_bind60269_h.jpg","caption":null,"order":8,"createdAt":"2025-03-27T23:41:11.088Z","updatedAt":"2025-03-27T23:41:11.088Z","deletedAt":null},{"id":"d89e2205-2f1b-4c89-bbd0-6e012f4864ac","productId":"9d6e3e40-0cfd-462e-b4fd-9470cc406fbe","url":"https://www.heomedia.com/img/nrm/x_bind60269_i.jpg","caption":null,"order":9,"createdAt":"2025-03-27T23:41:11.107Z","updatedAt":"2025-03-27T23:41:11.107Z","deletedAt":null}]}