{"data":[{"id":"393de356-e53c-4aa5-93cb-702aa9d163fe","productId":"b0fadd6e-a7db-4491-ad3e-8f48e8d38e0f","url":"https://www.heomedia.com/img/nrm/x_sqr100047.jpg","caption":null,"order":0,"createdAt":"2025-03-28T02:21:28.694Z","updatedAt":"2025-03-28T02:21:28.694Z","deletedAt":null},{"id":"6bf1c458-6fa6-41f3-a8a0-a5506794ee0f","productId":"b0fadd6e-a7db-4491-ad3e-8f48e8d38e0f","url":"https://www.heomedia.com/img/nrm/x_sqr100047_a.jpg","caption":null,"order":1,"createdAt":"2025-03-28T02:21:28.871Z","updatedAt":"2025-03-28T02:21:28.871Z","deletedAt":null},{"id":"46beeecd-dc18-4df6-bd6f-09822423e087","productId":"b0fadd6e-a7db-4491-ad3e-8f48e8d38e0f","url":"https://www.heomedia.com/img/nrm/x_sqr100047_b.jpg","caption":null,"order":2,"createdAt":"2025-03-28T02:21:28.881Z","updatedAt":"2025-03-28T02:21:28.881Z","deletedAt":null},{"id":"fcf83147-4b21-47d4-b806-e68b32f8bc8d","productId":"b0fadd6e-a7db-4491-ad3e-8f48e8d38e0f","url":"https://www.heomedia.com/img/nrm/x_sqr100047_c.jpg","caption":null,"order":3,"createdAt":"2025-03-28T02:21:28.889Z","updatedAt":"2025-03-28T02:21:28.889Z","deletedAt":null},{"id":"ef166b2c-860f-48ce-aec9-03c17b87e77b","productId":"b0fadd6e-a7db-4491-ad3e-8f48e8d38e0f","url":"https://www.heomedia.com/img/nrm/x_sqr100047_d.jpg","caption":null,"order":4,"createdAt":"2025-03-28T02:21:28.898Z","updatedAt":"2025-03-28T02:21:28.898Z","deletedAt":null},{"id":"d8ff1c94-72aa-41b7-97d2-fdabaf8c951f","productId":"b0fadd6e-a7db-4491-ad3e-8f48e8d38e0f","url":"https://www.heomedia.com/img/nrm/x_sqr100047_e.jpg","caption":null,"order":5,"createdAt":"2025-03-28T02:21:28.906Z","updatedAt":"2025-03-28T02:21:28.906Z","deletedAt":null},{"id":"bcb819ff-7165-4d1b-9c5d-68460b9a079c","productId":"b0fadd6e-a7db-4491-ad3e-8f48e8d38e0f","url":"https://www.heomedia.com/img/nrm/x_sqr100047_f.jpg","caption":null,"order":6,"createdAt":"2025-03-28T02:21:28.913Z","updatedAt":"2025-03-28T02:21:28.913Z","deletedAt":null},{"id":"1ac64626-aaae-42ca-966d-637a56f6fa7f","productId":"b0fadd6e-a7db-4491-ad3e-8f48e8d38e0f","url":"https://www.heomedia.com/img/nrm/x_sqr100047_g.jpg","caption":null,"order":7,"createdAt":"2025-03-28T02:21:28.922Z","updatedAt":"2025-03-28T02:21:28.922Z","deletedAt":null},{"id":"3eb46403-0ff2-4bcb-986b-decc8d219a8a","productId":"b0fadd6e-a7db-4491-ad3e-8f48e8d38e0f","url":"https://www.heomedia.com/img/nrm/x_sqr100047_h.jpg","caption":null,"order":8,"createdAt":"2025-03-28T02:21:28.932Z","updatedAt":"2025-03-28T02:21:28.932Z","deletedAt":null},{"id":"94a76624-2777-4f9b-b814-1b0dba225b92","productId":"b0fadd6e-a7db-4491-ad3e-8f48e8d38e0f","url":"https://www.heomedia.com/img/nrm/x_sqr100047_i.jpg","caption":null,"order":9,"createdAt":"2025-03-28T02:21:28.941Z","updatedAt":"2025-03-28T02:21:28.941Z","deletedAt":null},{"id":"a7a87047-523f-4ad5-be36-9f836d614b40","productId":"b0fadd6e-a7db-4491-ad3e-8f48e8d38e0f","url":"https://www.heomedia.com/img/nrm/x_sqr100047_j.jpg","caption":null,"order":10,"createdAt":"2025-03-28T02:21:28.950Z","updatedAt":"2025-03-28T02:21:28.950Z","deletedAt":null},{"id":"55665d14-fe71-43f7-8a6b-5165425967ba","productId":"b0fadd6e-a7db-4491-ad3e-8f48e8d38e0f","url":"https://www.heomedia.com/img/nrm/x_sqr100047_k.jpg","caption":null,"order":11,"createdAt":"2025-03-28T02:21:28.958Z","updatedAt":"2025-03-28T02:21:28.958Z","deletedAt":null}]}