{"data":[{"id":"8f09d63e-f013-4d5d-853c-332a8ff78fa3","productId":"b9b3982d-7bdf-4f6f-90b7-d4f68b0d0011","url":"https://www.heomedia.com/img/nrm/x_nmsk-ns5225.jpg","caption":null,"order":0,"createdAt":"2025-03-28T01:41:28.835Z","updatedAt":"2025-03-28T01:41:28.835Z","deletedAt":null},{"id":"c16f2194-e36f-4c97-8579-d6f8ed0f039b","productId":"b9b3982d-7bdf-4f6f-90b7-d4f68b0d0011","url":"https://www.heomedia.com/img/nrm/x_nmsk-ns5225_a.jpg","caption":null,"order":1,"createdAt":"2025-03-28T01:41:28.923Z","updatedAt":"2025-03-28T01:41:28.923Z","deletedAt":null},{"id":"1c596a7e-5146-4f1a-9196-1f7c99c3209b","productId":"b9b3982d-7bdf-4f6f-90b7-d4f68b0d0011","url":"https://www.heomedia.com/img/nrm/x_nmsk-ns5225_b.jpg","caption":null,"order":2,"createdAt":"2025-03-28T01:41:28.942Z","updatedAt":"2025-03-28T01:41:28.942Z","deletedAt":null}]}