{"data":[{"id":"4c4d5c99-27d3-4ff8-bb8e-5d8edc0bf2c3","productId":"f1847d19-9fda-480f-b169-cbb5a911db3d","url":"https://www.heomedia.com/img/nrm/x_vrt47203.jpg","caption":null,"order":0,"createdAt":"2025-03-28T02:41:04.578Z","updatedAt":"2025-03-28T02:41:04.578Z","deletedAt":null},{"id":"ab0d8e77-b7bd-418c-8004-a36aeaf7bbd8","productId":"f1847d19-9fda-480f-b169-cbb5a911db3d","url":"https://www.heomedia.com/img/nrm/x_vrt47203_a.jpg","caption":null,"order":1,"createdAt":"2025-03-28T02:41:04.733Z","updatedAt":"2025-03-28T02:41:04.733Z","deletedAt":null},{"id":"cd30825e-e659-4689-9c09-50bb462f08a1","productId":"f1847d19-9fda-480f-b169-cbb5a911db3d","url":"https://www.heomedia.com/img/nrm/x_vrt47203_b.jpg","caption":null,"order":2,"createdAt":"2025-03-28T02:41:04.754Z","updatedAt":"2025-03-28T02:41:04.754Z","deletedAt":null},{"id":"69a1c351-b267-401e-baef-1058a3a433e3","productId":"f1847d19-9fda-480f-b169-cbb5a911db3d","url":"https://www.heomedia.com/img/nrm/x_vrt47203_c.jpg","caption":null,"order":3,"createdAt":"2025-03-28T02:41:04.776Z","updatedAt":"2025-03-28T02:41:04.776Z","deletedAt":null},{"id":"04fa1686-e828-40cd-927d-a2520d3067c6","productId":"f1847d19-9fda-480f-b169-cbb5a911db3d","url":"https://www.heomedia.com/img/nrm/x_vrt47203_d.jpg","caption":null,"order":4,"createdAt":"2025-03-28T02:41:04.797Z","updatedAt":"2025-03-28T02:41:04.797Z","deletedAt":null},{"id":"102fbc82-7cb9-4688-b01f-6be29f30c510","productId":"f1847d19-9fda-480f-b169-cbb5a911db3d","url":"https://www.heomedia.com/img/nrm/x_vrt47203_e.jpg","caption":null,"order":5,"createdAt":"2025-03-28T02:41:04.818Z","updatedAt":"2025-03-28T02:41:04.818Z","deletedAt":null},{"id":"231be26e-84d1-4ee2-a55c-cc80ea7ab6fb","productId":"f1847d19-9fda-480f-b169-cbb5a911db3d","url":"https://www.heomedia.com/img/nrm/x_vrt47203_f.jpg","caption":null,"order":6,"createdAt":"2025-03-28T02:41:04.838Z","updatedAt":"2025-03-28T02:41:04.838Z","deletedAt":null},{"id":"3c05c9a7-f863-4d10-b359-f682f0b5cebf","productId":"f1847d19-9fda-480f-b169-cbb5a911db3d","url":"https://www.heomedia.com/img/nrm/x_vrt47203_g.jpg","caption":null,"order":7,"createdAt":"2025-03-28T02:41:04.859Z","updatedAt":"2025-03-28T02:41:04.859Z","deletedAt":null},{"id":"3680b746-e6e1-4ee6-9ff1-6032fd590b58","productId":"f1847d19-9fda-480f-b169-cbb5a911db3d","url":"https://www.heomedia.com/img/nrm/x_vrt47203_h.jpg","caption":null,"order":8,"createdAt":"2025-03-28T02:41:04.881Z","updatedAt":"2025-03-28T02:41:04.881Z","deletedAt":null},{"id":"f8541837-4ff8-49ee-993f-fab275317b38","productId":"f1847d19-9fda-480f-b169-cbb5a911db3d","url":"https://www.heomedia.com/img/nrm/x_vrt47203_i.jpg","caption":null,"order":9,"createdAt":"2025-03-28T02:41:04.908Z","updatedAt":"2025-03-28T02:41:04.908Z","deletedAt":null}]}