{"id":"144efa2c-2348-4fd4-8bf6-6d1134e8e0f1","name":"Naruto: Shippuden FiGPiN #1377 Naruto Uzumaki","slug":"naruto-shippuden-figpin-1377-naruto-uzum","description":null,"metaTitle":null,"metaDescription":null,"model":null,"releaseDate":null,"image":"/placeholder.svg","condition":null,"edition":null,"rarity":null,"features":null,"specifications":null,"createdAt":"2025-04-07T13:08:18.624Z","updatedAt":"2025-04-15T15:38:20.723Z","barcode":"7b591820-571f-484b-80d2-2c9772f14967","deletedAt":null,"source":"scraped","hasFakeBarcode":true,"duplicateId":null,"brandId":"4c3fc237-85d1-49cc-8943-a7230f33c0fa","franchiseId":null,"seriesId":null,"lineId":null,"categories":[{"productId":"144efa2c-2348-4fd4-8bf6-6d1134e8e0f1","categoryId":"c6ea4121-907d-426e-8774-80e229d31d4c","category":{"id":"c6ea4121-907d-426e-8774-80e229d31d4c","name":"Collectibles","slug":"collectibles","description":"Collectible items","image":null,"parentId":null,"createdAt":"2025-03-27T23:28:51.587Z","updatedAt":"2025-04-19T17:16:28.529Z","deletedAt":null}}],"retailerPrices":[{"id":"92098955-b9f4-4ec0-bb26-da5d4c558253","productId":"144efa2c-2348-4fd4-8bf6-6d1134e8e0f1","retailerId":"518d99da-63d7-47fd-86d3-ae3a79cadb44","countryId":"cfa253f4-b9e1-4488-9eba-3ea3f0834e01","price":15,"shipping":8.9,"inStock":true,"isPreOrder":false,"url":"https://www.bigbadtoystore.com/Product/VariationDetails/279508?o=4","couponCode":null,"lastChecked":"2025-04-07T13:08:18.674Z","createdAt":"2025-04-07T13:08:18.674Z","updatedAt":"2025-04-19T17:16:12.703Z","deletedAt":null,"currency":"USD","regionId":null,"retailer":{"id":"518d99da-63d7-47fd-86d3-ae3a79cadb44","name":"Big Bad Toy Store","slug":"big-bad-toy-store","logo":null,"website":null,"isActive":true,"createdAt":"2025-03-30T12:21:06.800Z","updatedAt":"2025-03-30T12:21:06.800Z","deletedAt":null,"description":null,"shipping":0,"affiliateCode":null,"affiliateParamKey":null,"useAffiliateCode":false}}],"productMSRPs":[],"brand":{"id":"4c3fc237-85d1-49cc-8943-a7230f33c0fa","name":"Naruto","slug":"naruto","description":"Naruto","createdAt":"2025-04-03T23:08:00.014Z","updatedAt":"2025-04-03T23:08:00.014Z","deletedAt":null},"franchise":null,"series":null,"line":null,"images":[],"brandName":"Naruto","brandSlug":"naruto","franchiseName":null,"franchiseSlug":null,"seriesName":null,"seriesSlug":null,"lineName":null,"lineSlug":null,"retailerPricesIds":["92098955-b9f4-4ec0-bb26-da5d4c558253"],"productMSRPsIds":[]}