{"id":"24378a5e-ebc3-4fb8-962c-964158a2b119","name":"Disney Nano Metalfigs Diecast Mini Figures 18-Pack Wave 1 4 cm","slug":"disney-nano-metalfigs-diecast-mini-figu2","description":"From Jada Toys 'Nano Metalfigs' series comes this pack with 18 cool Diecast figures. Each one stands approx. 4 cm tall. They come in a window box packaging.","metaTitle":null,"metaDescription":null,"model":null,"releaseDate":null,"image":"https://www.nerdup.nl/media/catalog/product/cache/3159e405f825aa58a103b15aad345729/x/_/x_jada253075005.jpg","condition":null,"edition":null,"rarity":null,"features":null,"specifications":null,"createdAt":"2025-04-09T13:30:44.604Z","updatedAt":"2025-04-15T15:38:28.032Z","barcode":"4006333080142","deletedAt":null,"source":"heo","hasFakeBarcode":false,"duplicateId":null,"brandId":"03202154-9bcf-418d-b6cc-34991d545409","franchiseId":"c27c5fab-697f-488e-a9f1-a8c269b20657","seriesId":null,"lineId":null,"categories":[{"productId":"24378a5e-ebc3-4fb8-962c-964158a2b119","categoryId":"c6ea4121-907d-426e-8774-80e229d31d4c","category":{"id":"c6ea4121-907d-426e-8774-80e229d31d4c","name":"Collectibles","slug":"collectibles","description":"Collectible items","image":null,"parentId":null,"createdAt":"2025-03-27T23:28:51.587Z","updatedAt":"2025-04-19T17:16:28.529Z","deletedAt":null}}],"retailerPrices":[{"id":"426ce165-d2e0-4b70-bf9d-665ee2017f33","productId":"24378a5e-ebc3-4fb8-962c-964158a2b119","retailerId":"1b473d7e-4457-4f74-bdd4-4ed4d1c8358d","countryId":"2801967a-360d-4f35-b27c-e3d5ca481d8d","price":20,"shipping":8.9,"inStock":true,"isPreOrder":false,"url":"https://www.nerdup.nl/disney-nano-metalfigs-diecast-mini-figures-18-pack-wave-1-4-cm","couponCode":null,"lastChecked":"2025-04-09T13:30:44.940Z","createdAt":"2025-04-09T13:30:44.939Z","updatedAt":"2025-04-19T17:16:12.861Z","deletedAt":null,"currency":"EUR","regionId":null,"retailer":{"id":"1b473d7e-4457-4f74-bdd4-4ed4d1c8358d","name":"NerdUP","slug":"nerdup","logo":null,"website":null,"isActive":true,"createdAt":"2025-03-29T13:33:34.338Z","updatedAt":"2025-03-29T13:33:34.338Z","deletedAt":null,"description":null,"shipping":0,"affiliateCode":null,"affiliateParamKey":null,"useAffiliateCode":false}},{"id":"d524e767-029e-4315-b48b-d6913dec7560","productId":"24378a5e-ebc3-4fb8-962c-964158a2b119","retailerId":"1f7a3891-8fef-4c6c-a126-a2b4ba9e899a","countryId":"2801967a-360d-4f35-b27c-e3d5ca481d8d","price":55.99,"shipping":8.9,"inStock":true,"isPreOrder":false,"url":"https://www.merchoid.com/nl/disney-nano-metalfigs-diecast-mini-figures-18-pack-wave-1-4cm/","couponCode":null,"lastChecked":"2025-04-17T12:00:20.915Z","createdAt":"2025-04-17T12:00:20.914Z","updatedAt":"2025-04-19T17:16:12.816Z","deletedAt":null,"currency":"EUR","regionId":null,"retailer":{"id":"1f7a3891-8fef-4c6c-a126-a2b4ba9e899a","name":"Merchoid Netherlands","slug":"merchoid-netherlands","logo":null,"website":null,"isActive":true,"createdAt":"2025-03-28T18:07:01.635Z","updatedAt":"2025-03-28T18:07:01.635Z","deletedAt":null,"description":null,"shipping":0,"affiliateCode":null,"affiliateParamKey":null,"useAffiliateCode":false}}],"productMSRPs":[],"brand":{"id":"03202154-9bcf-418d-b6cc-34991d545409","name":"Jada Toys","slug":"jada-toys","description":"Auto-imported brand: Jada Toys","createdAt":"2025-03-28T00:53:17.192Z","updatedAt":"2025-03-28T00:53:17.192Z","deletedAt":null},"franchise":{"id":"c27c5fab-697f-488e-a9f1-a8c269b20657","name":"Disney","slug":"disney","description":"Auto-imported theme: Disney","createdAt":"2025-03-27T23:41:15.948Z","updatedAt":"2025-04-19T17:16:32.627Z","deletedAt":null},"series":null,"line":null,"images":[{"url":"https://www.heomedia.com/img/nrm/d_jada253075005.jpg","caption":null,"order":1},{"url":"https://www.nerdup.nl/media/catalog/product/cache/3159e405f825aa58a103b15aad345729/x/_/x_jada253075005.jpg","caption":null,"order":2}],"brandName":"Jada Toys","brandSlug":"jada-toys","franchiseName":"Disney","franchiseSlug":"disney","seriesName":null,"seriesSlug":null,"lineName":null,"lineSlug":null,"retailerPricesIds":["426ce165-d2e0-4b70-bf9d-665ee2017f33","d524e767-029e-4315-b48b-d6913dec7560"],"productMSRPsIds":[]}