{"id":"42ad9439-6254-453b-aa9d-ad49f1e18e24","name":"Sailor Moon Look Up PVC Statue Eternal Sailor Jupiter & Eternal Sailor Venus 11 cm","slug":"sailor-moon-look-up-pvc-statue-eternal-s","description":null,"metaTitle":null,"metaDescription":null,"model":null,"releaseDate":null,"image":"https://www.heomedia.com/img/nrm/x_meho837159.jpg","condition":null,"edition":null,"rarity":null,"features":null,"specifications":"{\"dimensions\":{\"manufacturer\":{\"width\":\"175\",\"length\":\"262\",\"height\":\"130\",\"weight\":\"556\"},\"validated\":{\"width\":\"175\",\"length\":\"262\",\"height\":\"130\",\"weight\":\"556\"}},\"countryOfOrigin\":\"CN\",\"tariffNumber\":\"95030095\",\"ageRating\":\"15\",\"vatType\":\"NORMAL\",\"isEndOfLife\":true}","createdAt":"2025-03-28T01:21:49.185Z","updatedAt":"2025-03-30T20:19:22.960Z","barcode":"4535123837159","deletedAt":null,"source":"heo","hasFakeBarcode":false,"duplicateId":null,"brandId":"4d5e64a4-15da-48a6-82c8-1559f1fd0676","franchiseId":"14b669fb-61e9-4625-ae1b-f3f7ffe40803","seriesId":null,"lineId":"68b25bec-323f-432b-9f7a-1e5830ded5cb","categories":[{"productId":"42ad9439-6254-453b-aa9d-ad49f1e18e24","categoryId":"6b70b8de-7995-4cb0-a862-c09b7b6db787","category":{"id":"6b70b8de-7995-4cb0-a862-c09b7b6db787","name":"Manga & Anime","slug":"manga-and-anime","description":"Auto-imported category: Manga & Anime","image":null,"parentId":null,"createdAt":"2025-03-27T23:31:36.347Z","updatedAt":"2025-03-27T23:31:36.347Z","deletedAt":null}}],"retailerPrices":[],"productMSRPs":[{"id":"aa983a2c-4da5-4c72-aa4b-6c6930bdf0d7","productId":"42ad9439-6254-453b-aa9d-ad49f1e18e24","countryId":"2801967a-360d-4f35-b27c-e3d5ca481d8d","price":129,"currency":"EUR","createdAt":"2025-03-28T01:21:49.406Z","updatedAt":"2025-03-28T01:21:49.406Z","deletedAt":null,"regionId":null}],"brand":{"id":"4d5e64a4-15da-48a6-82c8-1559f1fd0676","name":"Megahouse","slug":"megahouse","description":"Auto-imported brand: Megahouse","createdAt":"2025-03-28T01:21:15.149Z","updatedAt":"2025-03-28T01:21:15.149Z","deletedAt":null},"franchise":{"id":"14b669fb-61e9-4625-ae1b-f3f7ffe40803","name":"Sailor Moon","slug":"sailor-moon","description":"Auto-imported theme: Sailor Moon","createdAt":"2025-03-27T23:38:07.460Z","updatedAt":"2025-03-27T23:38:07.460Z","deletedAt":null},"series":null,"line":{"id":"68b25bec-323f-432b-9f7a-1e5830ded5cb","name":"Statues","slug":"statues","description":"Auto-imported type: Statues","createdAt":"2025-03-27T23:32:19.601Z","updatedAt":"2025-03-27T23:32:19.601Z","deletedAt":null},"images":[{"url":"https://www.heomedia.com/img/nrm/x_meho837159.jpg","caption":null,"order":0},{"url":"https://www.heomedia.com/img/nrm/x_meho837159_a.jpg","caption":null,"order":1},{"url":"https://www.heomedia.com/img/nrm/x_meho837159_b.jpg","caption":null,"order":2},{"url":"https://www.heomedia.com/img/nrm/x_meho837159_c.jpg","caption":null,"order":3},{"url":"https://www.heomedia.com/img/nrm/x_meho837159_d.jpg","caption":null,"order":4},{"url":"https://www.heomedia.com/img/nrm/x_meho837159_e.jpg","caption":null,"order":5},{"url":"https://www.heomedia.com/img/nrm/x_meho837159_f.jpg","caption":null,"order":6},{"url":"https://www.heomedia.com/img/nrm/x_meho837159_g.jpg","caption":null,"order":7},{"url":"https://www.heomedia.com/img/nrm/x_meho837159_h.jpg","caption":null,"order":8},{"url":"https://www.heomedia.com/img/nrm/x_meho837159_i.jpg","caption":null,"order":9}],"brandName":"Megahouse","brandSlug":"megahouse","franchiseName":"Sailor Moon","franchiseSlug":"sailor-moon","seriesName":null,"seriesSlug":null,"lineName":"Statues","lineSlug":"statues","retailerPricesIds":[],"productMSRPsIds":["aa983a2c-4da5-4c72-aa4b-6c6930bdf0d7"]}