{"id":"fc3969a3-782a-402e-8af4-8f1871de12ac","name":"Rocky III Statue 1/3 Rocky 66 cm","slug":"rocky-iii-statue-1-3-rocky-66-cm","description":null,"metaTitle":null,"metaDescription":null,"model":null,"releaseDate":null,"image":"https://www.heomedia.com/img/nrm/x_pcs912049.jpg","condition":null,"edition":null,"rarity":null,"features":null,"specifications":"{\"dimensions\":{\"manufacturer\":{\"width\":\"785\",\"length\":\"785\",\"height\":\"300\",\"weight\":\"18000\"},\"validated\":{\"width\":\"785\",\"length\":\"785\",\"height\":\"300\",\"weight\":\"18000\"}},\"countryOfOrigin\":\"CN\",\"tariffNumber\":\"39264000\",\"ageRating\":\"14\",\"vatType\":\"NORMAL\",\"isEndOfLife\":true}","createdAt":"2025-03-28T01:56:44.568Z","updatedAt":"2025-03-30T20:20:58.684Z","barcode":"712179859746","deletedAt":null,"source":"heo","hasFakeBarcode":false,"duplicateId":null,"brandId":"bc88f656-0d58-49d6-a91c-91c7611204a2","franchiseId":"a5759b53-3859-4f08-afa5-2c789c3de33e","seriesId":null,"lineId":"68b25bec-323f-432b-9f7a-1e5830ded5cb","categories":[{"productId":"fc3969a3-782a-402e-8af4-8f1871de12ac","categoryId":"c6ea4121-907d-426e-8774-80e229d31d4c","category":{"id":"c6ea4121-907d-426e-8774-80e229d31d4c","name":"Collectibles","slug":"collectibles","description":"Collectible items","image":null,"parentId":null,"createdAt":"2025-03-27T23:28:51.587Z","updatedAt":"2025-03-27T23:28:51.587Z","deletedAt":null}}],"retailerPrices":[],"productMSRPs":[{"id":"28bba331-d760-466c-96a2-da2703a881ee","productId":"fc3969a3-782a-402e-8af4-8f1871de12ac","countryId":"2801967a-360d-4f35-b27c-e3d5ca481d8d","price":1999,"currency":"EUR","createdAt":"2025-03-28T01:56:44.843Z","updatedAt":"2025-03-28T01:56:44.843Z","deletedAt":null,"regionId":null}],"brand":{"id":"bc88f656-0d58-49d6-a91c-91c7611204a2","name":"Premium Collectibles Studio","slug":"premium-collectibles-studio","description":"Auto-imported brand: Premium Collectibles Studio","createdAt":"2025-03-28T01:56:40.022Z","updatedAt":"2025-03-28T01:56:40.022Z","deletedAt":null},"franchise":{"id":"a5759b53-3859-4f08-afa5-2c789c3de33e","name":"Rocky","slug":"rocky","description":"Auto-imported theme: Rocky","createdAt":"2025-03-27T23:49:20.566Z","updatedAt":"2025-03-27T23:49:20.566Z","deletedAt":null},"series":null,"line":{"id":"68b25bec-323f-432b-9f7a-1e5830ded5cb","name":"Statues","slug":"statues","description":"Auto-imported type: Statues","createdAt":"2025-03-27T23:32:19.601Z","updatedAt":"2025-03-27T23:32:19.601Z","deletedAt":null},"images":[{"url":"https://www.heomedia.com/img/nrm/x_pcs912049.jpg","caption":null,"order":0},{"url":"https://www.heomedia.com/img/nrm/x_pcs912049_a.jpg","caption":null,"order":1},{"url":"https://www.heomedia.com/img/nrm/x_pcs912049_b.jpg","caption":null,"order":2},{"url":"https://www.heomedia.com/img/nrm/x_pcs912049_c.jpg","caption":null,"order":3},{"url":"https://www.heomedia.com/img/nrm/x_pcs912049_d.jpg","caption":null,"order":4},{"url":"https://www.heomedia.com/img/nrm/x_pcs912049_e.jpg","caption":null,"order":5},{"url":"https://www.heomedia.com/img/nrm/x_pcs912049_f.jpg","caption":null,"order":6},{"url":"https://www.heomedia.com/img/nrm/x_pcs912049_g.jpg","caption":null,"order":7},{"url":"https://www.heomedia.com/img/nrm/x_pcs912049_h.jpg","caption":null,"order":8},{"url":"https://www.heomedia.com/img/nrm/x_pcs912049_i.jpg","caption":null,"order":9},{"url":"https://www.heomedia.com/img/nrm/x_pcs912049_j.jpg","caption":null,"order":10},{"url":"https://www.heomedia.com/img/nrm/x_pcs912049_k.jpg","caption":null,"order":11},{"url":"https://www.heomedia.com/img/nrm/x_pcs912049_l.jpg","caption":null,"order":12},{"url":"https://www.heomedia.com/img/nrm/x_pcs912049_m.jpg","caption":null,"order":13},{"url":"https://www.heomedia.com/img/nrm/x_pcs912049_n.jpg","caption":null,"order":14},{"url":"https://www.heomedia.com/img/nrm/x_pcs912049_o.jpg","caption":null,"order":15},{"url":"https://www.heomedia.com/img/nrm/x_pcs912049_p.jpg","caption":null,"order":16},{"url":"https://www.heomedia.com/img/nrm/x_pcs912049_q.jpg","caption":null,"order":17},{"url":"https://www.heomedia.com/img/nrm/x_pcs912049_r.jpg","caption":null,"order":18},{"url":"https://www.heomedia.com/img/nrm/x_pcs912049_s.jpg","caption":null,"order":19},{"url":"https://www.heomedia.com/img/nrm/x_pcs912049_t.jpg","caption":null,"order":20},{"url":"https://www.heomedia.com/img/nrm/x_pcs912049_u.jpg","caption":null,"order":21},{"url":"https://www.heomedia.com/img/nrm/x_pcs912049_v.jpg","caption":null,"order":22},{"url":"https://www.heomedia.com/img/nrm/x_pcs912049_w.jpg","caption":null,"order":23},{"url":"https://www.heomedia.com/img/nrm/x_pcs912049_x.jpg","caption":null,"order":24},{"url":"https://www.heomedia.com/img/nrm/x_pcs912049_y.jpg","caption":null,"order":25}],"brandName":"Premium Collectibles Studio","brandSlug":"premium-collectibles-studio","franchiseName":"Rocky","franchiseSlug":"rocky","seriesName":null,"seriesSlug":null,"lineName":"Statues","lineSlug":"statues","retailerPricesIds":[],"productMSRPsIds":["28bba331-d760-466c-96a2-da2703a881ee"]}